MANIFEST.in
README.md
monbosapin
monbosapin.py
monbosapin.sh
setup.py
FSDNOEL/__init__.py
FSDNOEL/sapin.py
FSDNOEL.egg-info/PKG-INFO
FSDNOEL.egg-info/SOURCES.txt
FSDNOEL.egg-info/dependency_links.txt
FSDNOEL.egg-info/top_level.txt